[{
        "title": "xyz1",
        "description": "lorem ipsum ...."
    },
    {
        "title": "xyz2",
        "description": "lorem ipsum ...."
    },
    {
        "title": "xyz3",
        "description": ""
    },
    {
        "title": "xyz4",
        "description": "lorem ipsum ...."
    },
    {
        "title": "xyz1",
        "description": "lorem ipsum ...."
    },
    {
        "title": "xyz2",
        "description": "lorem ipsum ...."
    },
    {
        "title": "xyz3",
        "description": ""
    },
    {
        "title": "xyz4",
        "description": "lorem ipsum ...."
    },
    {
        "title": "xyz1",
        "description": "lorem ipsum ...."
    },
    {
        "title": "xyz2",
        "description": "lorem ipsum ...."
    },
    {
        "title": "xyz3",
        "description": ""
    },
    {
        "title": "xyz4",
        "description": "lorem ipsum ...."
    }
]